nu_waves/__init__.py
nu_waves/py.typed.py
nu_waves/version.py
nu_waves/backends/__init__.py
nu_waves/backends/interface.py
nu_waves/backends/numpy_backend.py
nu_waves/backends/torch_backend.py
nu_waves/hamiltonian/base.py
nu_waves/matter/landau.py
nu_waves/matter/prem.py
nu_waves/matter/profile.py
nu_waves/matter/solar.py
nu_waves/matter/supernova.py
nu_waves/models/mixing.py
nu_waves/models/spectrum.py
nu_waves/propagation/oscillator.py
nu_waves/sources/sun.py
nu_waves/utils/flavors.py
nu_waves/utils/style.py
nu_waves/utils/units.py
nu_waves-1.0.3.dist-info/METADATA
nu_waves-1.0.3.dist-info/WHEEL
nu_waves-1.0.3.dist-info/licenses/LICENSE
nu_waves-1.0.3.dist-info/RECORD
