Metadata-Version: 2.4
Name: nu-waves
Version: 1.0.3
Summary: Flavour-oscillation probabilities for neutrinos with numpy/torch backends.
Project-URL: Homepage, https://github.com/nadrino/neutrino-interferometry
Project-URL: Issues, https://github.com/nadrino/neutrino-interferometry/issues
Author: Nadrino
License: LGPL-2.1-or-later
License-File: LICENSE
Keywords: PMNS,neutrino,oscillations,physics
Classifier: Development Status :: 3 - Alpha
Classifier: Intended Audience :: Science/Research
Classifier: License :: OSI Approved :: GNU Lesser General Public License v2 or later (LGPLv2+)
Classifier: Programming Language :: Python :: 3 :: Only
Classifier: Programming Language :: Python :: 3.9
Classifier: Programming Language :: Python :: 3.10
Classifier: Programming Language :: Python :: 3.11
Classifier: Programming Language :: Python :: 3.12
Classifier: Topic :: Scientific/Engineering :: Physics
Classifier: Typing :: Typed
Requires-Python: >=3.9
Requires-Dist: numpy>=1.24
Requires-Dist: torch>=2.0; platform_machine != 'wasm32'
Requires-Dist: tqdm
Provides-Extra: dev
Requires-Dist: build; extra == 'dev'
Requires-Dist: matplotlib; extra == 'dev'
Requires-Dist: mypy; extra == 'dev'
Requires-Dist: numpy; extra == 'dev'
Requires-Dist: pytest-cov; extra == 'dev'
Requires-Dist: pytest>=7; extra == 'dev'
Requires-Dist: ruff; extra == 'dev'
Requires-Dist: torch; extra == 'dev'
Requires-Dist: tqdm; extra == 'dev'
Requires-Dist: twine; extra == 'dev'
Provides-Extra: plot
Requires-Dist: matplotlib>=3.7; extra == 'plot'
Provides-Extra: torch
Requires-Dist: torch>=2.0; (platform_machine != 'wasm32') and extra == 'torch'
